paddlers/__init__.py
paddlers/custom_models/__init__.py
paddlers/custom_models/cd/__init__.py
paddlers/custom_models/cd/bit.py
paddlers/custom_models/cd/cdnet.py
paddlers/custom_models/cd/changestar.py
paddlers/custom_models/cd/dsamnet.py
paddlers/custom_models/cd/dsifn.py
paddlers/custom_models/cd/fc_ef.py
paddlers/custom_models/cd/fc_siam_conc.py
paddlers/custom_models/cd/fc_siam_diff.py
paddlers/custom_models/cd/param_init.py
paddlers/custom_models/cd/snunet.py
paddlers/custom_models/cd/stanet.py
paddlers/custom_models/cd/backbones/__init__.py
paddlers/custom_models/cd/backbones/resnet.py
paddlers/custom_models/cd/layers/__init__.py
paddlers/custom_models/cd/layers/attention.py
paddlers/custom_models/cd/layers/blocks.py
paddlers/custom_models/cls/__init__.py
paddlers/custom_models/cls/condensenet_v2.py
paddlers/custom_models/det/__init__.py
paddlers/custom_models/gan/__init__.py
paddlers/custom_models/gan/rcan_model.py
paddlers/custom_models/gan/generators/__init__.py
paddlers/custom_models/gan/generators/builder.py
paddlers/custom_models/gan/generators/rcan.py
paddlers/custom_models/seg/__init__.py
paddlers/custom_models/seg/farseg.py
paddlers/custom_models/seg/layers/__init__.py
paddlers/custom_models/seg/layers/layers_lib.py
paddlers/custom_models/seg/layers/param_init.py
paddlers/datasets/__init__.py
paddlers/datasets/cd_dataset.py
paddlers/datasets/clas_dataset.py
paddlers/datasets/coco.py
paddlers/datasets/seg_dataset.py
paddlers/datasets/sr_dataset.py
paddlers/datasets/voc.py
paddlers/deploy/__init__.py
paddlers/deploy/predictor.py
paddlers/models/__init__.py
paddlers/models/ppcls/__init__.py
paddlers/models/ppcls/arch/__init__.py
paddlers/models/ppcls/arch/utils.py
paddlers/models/ppcls/arch/backbone/__init__.py
paddlers/models/ppcls/arch/backbone/base/__init__.py
paddlers/models/ppcls/arch/backbone/base/theseus_layer.py
paddlers/models/ppcls/arch/backbone/legendary_models/__init__.py
paddlers/models/ppcls/arch/backbone/legendary_models/esnet.py
paddlers-1.0b0.dist-info/LICENSE
paddlers-1.0b0.dist-info/METADATA
paddlers-1.0b0.dist-info/WHEEL
paddlers-1.0b0.dist-info/top_level.txt
paddlers-1.0b0.dist-info/RECORD
