Metadata-Version: 2.1
Name: paddlers
Version: 1.0b0
Summary: Awesome Remote Sensing Toolkit based on PaddlePaddle
Home-page: https://github.com/PaddleCV-SIG/PaddleRS
Author: PaddleRS Authors
Author-email: 
License: Apache 2.0
Platform: UNKNOWN
Classifier: Programming Language :: Python :: 3.7
Classifier: Programming Language :: Python :: 3.8
Classifier: Programming Language :: Python :: 3.9
Classifier: License :: OSI Approved :: Apache Software License
Classifier: Operating System :: OS Independent
Requires-Python: >=3.7
License-File: LICENSE
Requires-Dist: paddleslim (>=2.2.1)
Requires-Dist: visualdl (>=2.1.1)
Requires-Dist: opencv-contrib-python (==4.3.0.38)
Requires-Dist: numba (==0.53.1)
Requires-Dist: scikit-learn (==0.23.2)
Requires-Dist: scikit-image (>=0.14.0)
Requires-Dist: pandas
Requires-Dist: scipy
Requires-Dist: cython
Requires-Dist: pycocotools
Requires-Dist: shapely
Requires-Dist: lap
Requires-Dist: motmetrics
Requires-Dist: chardet
Requires-Dist: openpyxl
Requires-Dist: easydict
Requires-Dist: munch
Requires-Dist: natsort
Requires-Dist: geojson
Requires-Dist: colorama
